dimensionality_reductions_jmsv/__init__.py
dimensionality_reductions_jmsv/cluster/_KMeans.py
dimensionality_reductions_jmsv/cluster/_KMedoids.py
dimensionality_reductions_jmsv/cluster/__init__.py
dimensionality_reductions_jmsv/decomposition/_PCA.py
dimensionality_reductions_jmsv/decomposition/_SVD.py
dimensionality_reductions_jmsv/decomposition/__init__.py
dimensionality_reductions_jmsv/manifold/_TSNE.py
dimensionality_reductions_jmsv/manifold/__init__.py
dimensionality_reductions_jmsv-0.2.0.dist-info/LICENSE
dimensionality_reductions_jmsv-0.2.0.dist-info/METADATA
dimensionality_reductions_jmsv-0.2.0.dist-info/WHEEL
dimensionality_reductions_jmsv-0.2.0.dist-info/RECORD
