Metadata-Version: 2.1
Name: dimensionality-reductions-jmsv
Version: 0.2.0
Summary: Package with the PCA, SVD and t-SNE methods for dimensionality reduction. It also contains the clustering algorithms K-Means and K-Medoids.
Home-page: https://pypi.org/project/dimensionality_reductions_jmsv/#history
License: MIT
Keywords: SVD,PCA,t-SNE,KMeans,KMedoids
Author: Mauricio Sierra
Maintainer: Send_Mail
Maintainer-email: mauricio@gmail.com
Requires-Python: >=3.10,<4.0
Classifier: Development Status :: 4 - Beta
Classifier: License :: OSI Approved :: MIT License
Classifier: Programming Language :: Python :: 3
Classifier: Programming Language :: Python :: 3.10
Classifier: Programming Language :: Python :: 3.11
Classifier: Programming Language :: Python :: 3.10
Requires-Dist: numpy (>=1.24.2,<2.0.0)
Project-URL: Repository, https://github.com/mauriciosierrav/dimensionality-reduction-jmsv.git
